portia_fxrates/__init__.py
portia_fxrates/__main__.py
portia_fxrates/openfxrates.py
portia_fxrates-0.1.0.dist-info/DESCRIPTION.rst
portia_fxrates-0.1.0.dist-info/METADATA
portia_fxrates-0.1.0.dist-info/RECORD
portia_fxrates-0.1.0.dist-info/WHEEL
portia_fxrates-0.1.0.dist-info/entry_points.txt
portia_fxrates-0.1.0.dist-info/metadata.json
portia_fxrates-0.1.0.dist-info/top_level.txt
