Metadata-Version: 2.0
Name: portia-fxrates
Version: 0.1.0
Summary: Download FX rates frop OpenFX
Home-page: https://github.com/tomanizer/portia_fxrates
Author: Thomas Haederle
Author-email: thomas.haederle@portiafrances.com
License: MIT
Keywords: portia_fxrates
Platform: UNKNOWN
Classifier: Development Status :: 2 - Pre-Alpha
Classifier: Intended Audience :: Developers
Classifier: License :: OSI Approved :: MIT License
Classifier: Natural Language :: English
Classifier: Programming Language :: Python :: 3
Classifier: Programming Language :: Python :: 3.3
Classifier: Programming Language :: Python :: 3.4
Classifier: Programming Language :: Python :: 3.5
Classifier: Programming Language :: Python :: 3.6
Requires-Dist: apiwrapper
Requires-Dist: pandas
